nukiwebapi/__init__.py
nukiwebapi/account.py
nukiwebapi/account_user.py
nukiwebapi/address.py
nukiwebapi/address_reservation.py
nukiwebapi/address_token.py
nukiwebapi/advanced_api.py
nukiwebapi/api_key.py
nukiwebapi/company.py
nukiwebapi/notification.py
nukiwebapi/nuki_web_api.py
nukiwebapi/opener.py
nukiwebapi/service.py
nukiwebapi/smartlock.py
nukiwebapi/smartlock_auth.py
nukiwebapi/smartlock_instance.py
nukiwebapi/smartlock_log.py
nuki_web_api-0.1.12.dist-info/METADATA
nuki_web_api-0.1.12.dist-info/WHEEL
nuki_web_api-0.1.12.dist-info/top_level.txt
nuki_web_api-0.1.12.dist-info/RECORD
