Metadata-Version: 2.4
Name: nuki-web-api
Version: 0.1.12
Summary: A Python wrapper for the Nuki Web API
Author-email: barghest89 <blachosf@gmail.com>
License-Expression: MIT
Project-URL: Homepage, https://github.com/barghest89/nuki-web-api
Project-URL: Bug Tracker, https://github.com/barghest89/nuki-web-api/issues
Keywords: nuki,api,smartlock
Classifier: Development Status :: 3 - Alpha
Classifier: Programming Language :: Python :: 3.11
Requires-Dist: requests==2.32.5
Provides-Extra: dev
Requires-Dist: pytest; extra == "dev"
Requires-Dist: pytest-cov; extra == "dev"
Requires-Dist: python-dotenv; extra == "dev"
Requires-Dist: pyotp; extra == "dev"
